texto_tools/__init__.py
texto_tools_teogenesmoura-0.0.1.dist-info/LICENSE
texto_tools_teogenesmoura-0.0.1.dist-info/METADATA
texto_tools_teogenesmoura-0.0.1.dist-info/WHEEL
texto_tools_teogenesmoura-0.0.1.dist-info/top_level.txt
texto_tools_teogenesmoura-0.0.1.dist-info/RECORD
